efvaccination.py
efvaccination-0.0.1.dist-info/METADATA
efvaccination-0.0.1.dist-info/WHEEL
efvaccination-0.0.1.dist-info/entry_points.txt
efvaccination-0.0.1.dist-info/top_level.txt
efvaccination-0.0.1.dist-info/RECORD
