Metadata-Version: 2.1
Name: efvaccination
Version: 0.0.1
Summary: A program to show the effectiveness of vaccination with symptoms by age groups
Home-page: https://github.com/Ryumi-Ryumi/vaccination
Author: ryumiryumi
Author-email: ryumi.ryumi.super@gmail.com
License: UNKNOWN
Project-URL: Bug Tracker, https://github.com/Ryumi-Ryumi/vaccination
Platform: UNKNOWN
Classifier: Programming Language :: Python :: 3
Classifier: License :: OSI Approved :: MIT License
Classifier: Operating System :: OS Independent
Requires-Python: >=3.8
